Workbook

Sheet sheet1
A1: 订单号 | B1: 订单状态 | C1: 负责人（业务员） | D1: 买家名称 | E1: 下单时间 | F1: 付款时间 | G1: 订单金额 | H1: 商品编码 | I1: 完整收货地址 | J1: 收件人名称 | K1: 联系电话 | L1: 手机 | M1: 联系邮件 | N1: 详细地址 | O1: 邮编 | P1: 扩展城市（德/意/波/墨为真实的城市） | Q1: 城市 | R1: 州/省 | S1: 收货国家 | T1: 买家选择物流 | U1: 实际发货单号 | V1: 确认收货时间 | W1: 售后单
A2: 8207841133554507 | B2: 等待发货 | C2: default firstName default lastName | D2: Juan Valiente | E2: 01/16/2026 15:57 | F2: 01/16/2026 15:57 | G2: CN￥ 954.91 | H2: JKM-Y10-PRO * 1 | I2: 8400 NW 25th ST、Miami、Florida、United States | J2: juanpedrobm273605 | K2: +1 | L2: 8092584174 | M2: jprv@yahoo.com | N2: 8400 NW 25th ST | O2: 33122 | Q2: Miami | R2: Florida | S2: United States | T2: AE_US_SAVER | W2: =VLOOKUP(A2,[1]速卖通售后单!$A:$C,2,FALSE) -> #N/A
A3: 3067837993265173 | B3: 等待发货 | C3: default firstName default lastName | D3: Filippo Rosace | E3: 01/16/2026 15:16 | F3: 01/16/2026 15:20 | G3: CN￥ 213.71 | H3: GJ-JLLSD-055+RS1 * 1 | I3: Via Rogoredo 21\D C/O BarTabacchi、20138、Milano、Milano、Lombardia、Italy | J3: Gaia Magenis | K3: 39 | L3: 3490742334 | M3: filo984@hotmail.com | N3: Via Rogoredo 21\D C/O BarTabacchi | O3: 20138 | P3: Milano | Q3: Milano | R3: Lombardia | S3: Italy | T3: SELLER_SHIPPING_DE | W3: =VLOOKUP(A3,[1]速卖通售后单!$A:$C,2,FALSE) -> #N/A
A4: 8208947199356513 | B4: 等待发货 | C4: default firstName default lastName | D4: The Taser Gamer 01 user | E4: 01/16/2026 14:06 | F4: 01/16/2026 14:06 | G4: CN￥ 242.35 | H4: XLW-ele138-BK * 1 | I4: 7321 E 48th st 70-4、Tulsa、Oklahoma、United States | J4: Derrick Mayhue | K4: +1 | L4: 9188591400 | M4: coolguyyy8@gmail.com | N4: 7321 E 48th st 70-4 | O4: 74145 | Q4: Tulsa | R4: Oklahoma | S4: United States | T4: Seller Shpping | W4: =VLOOKUP(A4,[1]速卖通售后单!$A:$C,2,FALSE) -> #N/A
A5: 8208729252504396 | B5: 等待发货 | C5: default firstName default lastName | D5: US20251207ryPq user | E5: 01/16/2026 10:58 | F5: 01/16/2026 10:58 | G5: CN￥ 267.30 | H5: JKM@-ele180in1-BK * 1 | I5: 585 Yellow Jacket Road、Dayton、Nevada、United States | J5: Bruce Davis | K5: +1 | L5: 7755305675 | M5: us20251207rypq_28439@aliexpress.com | N5: 585 Yellow Jacket Road | O5: 89403 | Q5: Dayton | R5: Nevada | S5: United States | T5: AE_US_SAVER | W5: =VLOOKUP(A5,[1]速卖通售后单!$A:$C,2,FALSE) -> #N/A
A6: 3067803675386565 | B6: 等待发货 | C6: default firstName default lastName | D6: Wiśniewski Miłosz | E6: 01/16/2026 02:08 | F6: 01/16/2026 02:08 | G6: CN￥ 185.34 | H6: GJ-JLLSD-055+RS1 * 1 | I6: Sierakowskiego 49、87600、Lipno、Lipno、Kujawsko-Pomorskie、Poland | J6: Milosz Wisniewski | K6: +48 | L6: 606635682 | M6: rrdyzswcfx@privaterelay.appleid.com | N6: Sierakowskiego 49 | O6: 87600 | P6: Lipno | Q6: Lipno | R6: Kujawsko-Pomorskie | S6: Poland | T6: SELLER_SHIPPING_DE | W6: =VLOOKUP(A6,[1]速卖通售后单!$A:$C,2,FALSE) -> #N/A
A7: 3067432197955494 | B7: 等待买家收货 | C7: default firstName default lastName | D7: Yavor Raychev | E7: 01/15/2026 20:24 | F7: 01/15/2026 20:24 | G7: CN￥ 267.30 | H7: JKM@-ele180in1-BK * 1 | I7: 10850 NW 21st ST STE 200、Miami、Florida、United States | J7: Yavor Raychev PANAVANA | K7: +1 | L7: 3058508036 | M7: google_100238807703275667743@aliexpress.com | N7: 10850 NW 21st ST STE 200 | O7: 33172 | Q7: Miami | R7: Florida | S7: United States | T7: AE_US_SAVER | U7: AE_US_SAVER:UUS61G5650882228665 | W7: =VLOOKUP(A7,[1]速卖通售后单!$A:$C,2,FALSE) -> #N/A
A8: 3067515495155308 | B8: 等待买家收货 | C8: default firstName default lastName | D8: Jakub Gorzkiewicz | E8: 01/15/2026 17:51 | F8: 01/15/2026 17:51 | G8: CN￥ 342.58 | H8: JKM@-ELE180in1-Bk-D * 1 | I8: Władysława Króla 47 20、94039、Lodz、Lodzkie、Poland | J8: Jakub Gorzkiewicz | K8: +48 | L8: 798277255 | M8: japper@tlen.pl | N8: Władysława Króla 47 20 | O8: 94039 | Q8: Lodz | R8: Lodzkie | S8: Poland | T8: SELLER_SHIPPING_DE | U8: Seller Shpping DE :887960212963 | W8: =VLOOKUP(A8,[1]速卖通售后单!$A:$C,2,FALSE) -> #N/A
A9: 8207857760625849 | B9: 等待买家收货 | C9: default firstName default lastName | D9: Seovannys Jimenez | E9: 01/15/2026 16:15 | F9: 01/15/2026 16:15 | G9: CN￥ 241.76 | H9: JKM@-180in1-BK * 1 | I9: 8316 NW 68th ST Apt PC-10836、Miami、Florida、United States | J9: Seovannys Jimenez | K9: +1 | L9: 7863594823 | M9: seovannys.j.r@gmail.com | N9: 8316 NW 68th ST Apt PC-10836 | O9: 331662920 | Q9: Miami | R9: Florida | S9: United States | T9: AE_US_SAVER | U9: AE_US_SAVER:UUS61G5650881185519 | W9: =VLOOKUP(A9,[1]速卖通售后单!$A:$C,2,FALSE) -> #N/A
A10: 8208560225255823 | B10: 等待买家收货 | C10: default firstName default lastName | D10: Lorenzo Kevin | E10: 01/15/2026 10:29 | F10: 01/15/2026 10:32 | G10: CN￥ 267.30 | H10: JKM@-ele180in1-BK * 1 | I10: 13435 SW 290th ST、Homestead、Florida、United States | J10: Kevin Lorenzo Valdes | K10: +1 | L10: 7865019153 | M10: kevin547lorenzo@gmail.com | N10: 13435 SW 290th ST | O10: 33033 | Q10: Homestead | R10: Florida | S10: United States | T10: AE_US_SAVER | U10: AE_US_SAVER:UUS61G5650881185497 | W10: =VLOOKUP(A10,[1]速卖通售后单!$A:$C,2,FALSE) -> #N/A
A11: 8208915274070746 | B11: 等待买家收货 | C11: default firstName default lastName | D11: Reginald C | E11: 01/15/2026 10:08 | F11: 01/15/2026 10:08 | G11: CN￥ 267.30 | H11: JKM@-ele180in1-BK * 1 | I11: 250 ashland PL 12E、Brooklyn、New York、United States | J11: Reginald Coupet | K11: +1 | L11: 7188076064 | M11: reggieok2k@gmail.com | N11: 250 ashland PL 12E | O11: 11217 | Q11: Brooklyn | R11: New York | S11: United States | T11: Seller Shpping | U11: Seller Shipping US:GFUS01030164078403 | W11: =VLOOKUP(A11,[1]速卖通售后单!$A:$C,2,FALSE) -> #N/A
A12: 8207846565476069 | B12: 等待买家收货 | C12: default firstName default lastName | D12: trent t | E12: 01/15/2026 08:14 | F12: 01/15/2026 08:14 | G12: CN￥ 235.69 | H12: JKM@-180in1-Wh * 1 | I12: 571 Oceanside Blvd、Indialantic、Florida、United States | J12: Trent Carter | K12: +1 | L12: 3215364944 | M12: trent@trentcarter.com | N12: 571 Oceanside Blvd | O12: 32903 | Q12: Indialantic | R12: Florida | S12: United States | T12: AE_US_SAVER | U12: AE_US_SAVER:CNGF001FL6069000005942579 | W12: =VLOOKUP(A12,[1]速卖通售后单!$A:$C,2,FALSE) -> #N/A
A13: 8207845128809746 | B13: 等待发货 | C13: default firstName default lastName | D13: Juan Lozano | E13: 01/15/2026 07:19 | F13: 01/15/2026 07:19 | G13: CN￥ 152.02 | H13: MT-S1-Sliver * 1 | I13: 40 67 Hampton Street 3B、Elmhurst、New York、United States | J13: Juan M Lozano | K13: +1 | L13: 7184965958 | M13: lozanocjm.jl@gmail.com | N13: 40 67 Hampton Street 3B | O13: 11373 | Q13: Elmhurst | R13: New York | S13: United States | T13: USPS | W13: =VLOOKUP(A13,[1]速卖通售后单!$A:$C,2,FALSE) -> #N/A
A14: 8208695659680800 | B14: 等待发货 | C14: default firstName default lastName | D14: Przemyslaw Leja | E14: 01/15/2026 06:55 | F14: 01/15/2026 06:55 | G14: CN￥ 241.76 | H14: JKM@-180in1-BK * 1 | I14: 280 E houston ST THE HOUSTON LOBBY、New york、New York、United States | J14: DAVID DOORMAN | K14: +1 | L14: 9294226669 | M14: shayd93@gmail.com | N14: 280 E houston ST THE HOUSTON LOBBY | O14: 10002 | Q14: New york | R14: New York | S14: United States | T14: Seller Shpping | W14: =VLOOKUP(A14,[1]速卖通售后单!$A:$C,2,FALSE) -> #N/A
A15: 8208554949570800 | B15: 订单关闭 | C15: default firstName default lastName | D15: P**a | E15: 01/15/2026 06:34 | F15: 01/15/2026 06:34 | G15: CN￥ 235.69 | H15: JKM@-180in1-Wh * 1 | I15: ********uston ST THE HOUSTON LOBBY、New york、New York、United States | J15: DAVI********* | K15: +1 | L15: 92****6669 | M15: shay***@gmail.com | N15: **************************ON LOBBY | O15: 10002 | Q15: New york | R15: New York | S15: United States | T15: Seller Shpping | W15: =VLOOKUP(A15,[1]速卖通售后单!$A:$C,2,FALSE) -> #N/A
A16: 8208051399730819 | B16: 等待买家收货 | C16: default firstName default lastName | D16: Rivera Márquez Alejandro | E16: 01/15/2026 05:43 | F16: 01/15/2026 05:43 | G16: CN￥ 267.30 | H16: JKM@-ele180in1-BK * 1 | I16: 19010 NW 57th AVE Apt 105、Hialeah、Florida、United States | J16: Alejandro Rivera | K16: +1 | L16: 3058483876 | M16: 8jgg2jkm5r@privaterelay.appleid.com | N16: 19010 NW 57th AVE Apt 105 | O16: 33015 | Q16: Hialeah | R16: Florida | S16: United States | T16: AE_US_SAVER | U16: AE_US_SAVER:UUS61G5650881185483 | W16: =VLOOKUP(A16,[1]速卖通售后单!$A:$C,2,FALSE) -> #N/A
A17: 3067275143722078 | B17: 等待买家收货 | C17: default firstName default lastName | D17: wolfgangmw user | E17: 01/15/2026 03:02 | F17: 01/15/2026 03:02 | G17: CN￥ 201.59 | H17: MT-Ele68in-1 * 1 | I17: Am Nußbaum 20、35606、Solms、Lahn-Dill-Kreis、Hessen、Germany | J17: Wolfgang Menk | K17: +49 | L17: 15141266765 | M17: wolfgangmw@gmail.com | N17: Am Nußbaum 20 | O17: 35606 | P17: Solms | Q17: Lahn-Dill-Kreis | R17: Hessen | S17: Germany | T17: SELLER_SHIPPING_DE | U17: Seller Shpping DE :00340434798210050464 | W17: =VLOOKUP(A17,[1]速卖通售后单!$A:$C,2,FALSE) -> #N/A
A18: 3067472376709787 | B18: 等待买家收货 | C18: default firstName default lastName | D18: Bjoern Gloeckner | E18: 01/15/2026 01:43 | F18: 01/15/2026 01:43 | G18: CN￥ 320.81 | H18: JKM@-ELE180in1-Bk-D * 1 | I18: Poissystr. 11-13、66955、Pirmasens、Pirmasens、Rheinland-Pfalz、Germany | J18: Bjoern Gloeckner | K18: +49 | L18: 15201943629 | M18: online-order@cgon.de | N18: Poissystr. 11-13 | O18: 66955 | P18: Pirmasens | Q18: Pirmasens | R18: Rheinland-Pfalz | S18: Germany | T18: SELLER_SHIPPING_DE | U18: Seller Shpping DE :00340434798210050457 | W18: =VLOOKUP(A18,[1]速卖通售后单!$A:$C,2,FALSE) -> #N/A
A19: 8207897788125433 | B19: 等待买家收货 | C19: default firstName default lastName | D19: MX m | E19: 01/15/2026 01:14 | F19: 01/15/2026 01:14 | G19: CN￥ 267.30 | H19: JKM@-ele180in1-BK * 1 | I19: 37 le vista ln、Asheville、North Carolina、United States | J19: Miguel espino | K19: 1 | L19: 8282756716 | M19: miguelespino140@gmail.com | N19: 37 le vista ln | O19: 28806 | Q19: Asheville | R19: North Carolina | S19: United States | T19: Seller Shpping | U19: Seller Shipping US:GFUS01030164067072 | W19: =VLOOKUP(A19,[1]速卖通售后单!$A:$C,2,FALSE) -> #N/A
A20: 3067270585378930 | B20: 等待买家收货 | C20: default firstName default lastName | D20: Isaias Rodriguez Arnesto | E20: 01/15/2026 00:49 | F20: 01/15/2026 00:50 | G20: CN￥ 364.71 | H20: JKM@-ELE180in1-Bk-D * 1 | I20: CALLE ALCAZARQUIVIR N4 BAJO B、Sevilla、Sevilla、Spain | J20: Isaias Rodriguez Arnesto | K20: +34 | L20: 691497987 | M20: isaiasprivado@gmail.com | N20: CALLE ALCAZARQUIVIR N4 BAJO B | O20: 41015 | Q20: Sevilla | R20: Sevilla | S20: Spain | T20: SELLER_SHIPPING_DE | U20: Seller Shpping DE :887960212941 | W20: =VLOOKUP(A20,[1]速卖通售后单!$A:$C,2,FALSE) -> #N/A
A21: 8208444844585486 | B21: 等待买家收货 | C21: default firstName default lastName | D21: Wilson David | E21: 01/14/2026 20:12 | F21: 01/14/2026 20:12 | G21: CN￥ 235.04 | H21: JKM@-180in1-BK * 1 | I21: 8822 Silver Maple Drive、Ooltewah、Tennessee、United States | J21: David Wilson | K21: +1 | L21: 4237186438 | M21: fjmmpcznvw@privaterelay.appleid.com | N21: 8822 Silver Maple Drive | O21: 37363 | Q21: Ooltewah | R21: Tennessee | S21: United States | T21: AE_US_SAVER | U21: AE_US_SAVER:CNGF001FL5486000005996179 | W21: =VLOOKUP(A21,[1]速卖通售后单!$A:$C,2,FALSE) -> #N/A
A22: 8208443243441544 | B22: 等待买家收货 | C22: default firstName default lastName | D22: Stuart Vealey | E22: 01/14/2026 18:43 | F22: 01/14/2026 18:44 | G22: CN￥ 235.86 | H22: XGGJ23110201-180in1 * 1 | I22: 1438 battle creek RD、Charlotte、Michigan、United States | J22: Stuart Vealey | K22: +1 | L22: 5173032468 | M22: stuartvealey@gmail.com | N22: 1438 battle creek RD | O22: 48813 | Q22: Charlotte | R22: Michigan | S22: United States | T22: Seller Shpping | U22: Seller Shipping US:9234690382438000150098 | W22: =VLOOKUP(A22,[1]速卖通售后单!$A:$C,2,FALSE) -> #N/A
A23: 3067450457411762 | B23: 等待买家收货 | C23: default firstName default lastName | D23: DIVERSPORT SL | E23: 01/14/2026 12:34 | F23: 01/14/2026 12:34 | G23: CN￥ 209.31 | H23: GJ-JLLSD-055+RS1 * 1 | I23: AVDA SALVADOR DALI 29 1º1ª、Figueres、Girona、Spain | J23: DIVERSPORT SL B17711474 | K23: +34 | L23: 637304576 | M23: jrdrc51@gmail.com | N23: AVDA SALVADOR DALI 29 1º1ª | O23: 17600 | Q23: Figueres | R23: Girona | S23: Spain | T23: SELLER_SHIPPING_DE | U23: Seller Shpping DE :1Z11H4020420189831 | W23: =VLOOKUP(A23,[1]速卖通售后单!$A:$C,2,FALSE) -> #N/A
A24: 8208428127770939 | B24: 等待买家收货 | C24: default firstName default lastName | D24: pylan76 user | E24: 01/14/2026 08:18 | F24: 01/14/2026 08:18 | G24: CN￥ 242.35 | H24: XLW-ele138-BK * 1 | I24: 404 bent creek TRCE、Chelsea、Alabama、United States | J24: Dylan Williamson | K24: +1 | L24: 2056133310 | M24: pylan76@gmail.com | N24: 404 bent creek TRCE | O24: 35043 | Q24: Chelsea | R24: Alabama | S24: United States | T24: Seller Shpping | U24: Seller Shipping US:9234690382438000150081 | W24: =VLOOKUP(A24,[1]速卖通售后单!$A:$C,2,FALSE) -> #N/A
A25: 8207776654539314 | B25: 等待买家收货 | C25: default firstName default lastName | D25: chadhall71 user | E25: 01/14/2026 04:28 | F25: 01/14/2026 04:28 | G25: CN￥ 267.30 | H25: JKM@-ele180in1-BK * 1 | I25: 1035 meghan LN、King、North Carolina、United States | J25: John Hall | K25: +1 | L25: 3369724645 | M25: chadhall71@yahoo.com | N25: 1035 meghan LN | O25: 27021 | Q25: King | R25: North Carolina | S25: United States | T25: AE_US_SAVER | U25: AE_US_SAVER:CNGF001FL9314000005773556 | W25: =VLOOKUP(A25,[1]速卖通售后单!$A:$C,2,FALSE) -> #N/A
A26: 3067416850141821 | B26: 等待买家收货 | C26: default firstName default lastName | D26: jana user | E26: 01/14/2026 00:19 | F26: 01/14/2026 00:19 | G26: CN￥ 270.15 | H26: JKM@-180in1-Wh * 1 | I26: Am Zenterling 24b、91560、Heilsbronn、Ansbach、Bayern、Germany | J26: Jana Sennewald | K26: +49 | L26: 1714589744 | M26: jana@sennewald.run | N26: Am Zenterling 24b | O26: 91560 | P26: Heilsbronn | Q26: Ansbach | R26: Bayern | S26: Germany | T26: SELLER_SHIPPING_DE | U26: Seller Shpping DE :00340434798210049857 | W26: =VLOOKUP(A26,[1]速卖通售后单!$A:$C,2,FALSE) -> #N/A
A27: 8207868509596593 | B27: 等待买家收货 | C27: default firstName default lastName | D27: arshad.tj.ahmady user | E27: 01/13/2026 23:06 | F27: 01/13/2026 23:06 | G27: CN￥ 154.88 | H27: MT-S1-Sliver * 1 | I27: 18 cheechako rd、Buxton、Maine、United States | J27: Arshad Ahmady | K27: +1 | L27: 2072089270 | M27: arshad.tj.ahmady@gmail.com | N27: 18 cheechako rd | O27: 04093 | Q27: Buxton | R27: Maine | S27: United States | T27: AE_US_SAVER | U27: AE_US_SAVER:CNGF001FL6593000005852599 | W27: =VLOOKUP(A27,[1]速卖通售后单!$A:$C,2,FALSE) -> #N/A
A28: 8207769932313986 | B28: 等待买家收货 | C28: default firstName default lastName | D28: Leandro Alias | E28: 01/13/2026 20:07 | F28: 01/13/2026 20:07 | G28: CN￥ 235.69 | H28: JKM@-180in1-Wh * 1 | I28: 7815 NW 15th ST HUB logistic corp、Doral、Florida、United States | J28: leandro SOS LOGIC alias | K28: +1 | L28: 3056405422 | M28: aliasleandro@gmail.com | N28: 7815 NW 15th ST HUB logistic corp | O28: 33126 | Q28: Doral | R28: Florida | S28: United States | T28: AE_US_SAVER | U28: AE_US_SAVER:UUS61E5650868675098 | W28: =VLOOKUP(A28,[1]速卖通售后单!$A:$C,2,FALSE) -> #N/A
A29: 8207809447939581 | B29: 等待买家收货 | C29: default firstName default lastName | D29: Edgar Martinez | E29: 01/13/2026 19:42 | F29: 01/13/2026 19:42 | G29: CN￥ 235.69 | H29: JKM@-180in1-Wh * 1 | I29: 235 spring ST 2a、Ossining、New York、United States | J29: Edgar Martinez | K29: +1 | L29: 9142529142 | M29: roamingrepairs.llc@gmail.com | N29: 235 spring ST 2a | O29: 10562 | Q29: Ossining | R29: New York | S29: United States | T29: AE_US_SAVER | U29: AE_US_SAVER:UUS61E5650868675066 | W29: =VLOOKUP(A29,[1]速卖通售后单!$A:$C,2,FALSE) -> #N/A
A30: 8207862345420665 | B30: 等待买家收货 | C30: default firstName default lastName | D30: kiandeguzman18 user | E30: 01/13/2026 18:26 | F30: 01/13/2026 18:26 | G30: CN￥ 220.32 | H30: LX-RS66IN1 * 1 | I30: 36 Bog and Vly Ln、Lincoln park、New Jersey、United States | J30: Kristian Deguzman | K30: +1 | L30: 8622210699 | M30: kiandeguzman18@yahoo.com | N30: 36 Bog and Vly Ln | O30: 07035 | Q30: Lincoln park | R30: New Jersey | S30: United States | T30: AE_US_SAVER | U30: AE_US_SAVER:UUS61E5650868675078 | W30: =VLOOKUP(A30,[1]速卖通售后单!$A:$C,2,FALSE) -> #N/A
A31: 8207764016206690 | B31: 等待买家收货 | C31: default firstName default lastName | D31: DP White | E31: 01/13/2026 16:45 | F31: 01/13/2026 16:45 | G31: CN￥ 267.30 | H31: JKM@-ele180in1-BK * 1 | I31: 6404 Hwy 98 East, Comer, GA 30629、Madison County、Georgia、United States | J31: David Parks White | K31: +1 | L31: 7069556424 | M31: davidparkswhite@gmail.com | N31: 6404 Hwy 98 East, Comer, GA 30629 | O31: 30629 | Q31: Madison County | R31: Georgia | S31: United States | T31: AE_US_SAVER | U31: AE_US_SAVER:CNGF001FL6690000005769306 | W31: =VLOOKUP(A31,[1]速卖通售后单!$A:$C,2,FALSE) -> #N/A
A32: 8208011557663958 | B32: 等待买家收货 | C32: default firstName default lastName | D32: jon user | E32: 01/13/2026 15:37 | F32: 01/13/2026 15:37 | G32: CN￥ 241.76 | H32: JKM@-180in1-BK * 1 | I32: 49 crest AVE、Revere、Massachusetts、United States | J32: Jon Sargent | K32: +1 | L32: 8029893027 | M32: jon@kannedheatkitchen.com | N32: 49 crest AVE | O32: 02151 | Q32: Revere | R32: Massachusetts | S32: United States | T32: AE_US_SAVER | U32: AE_US_SAVER:UUS61E5650866917823 | W32: =VLOOKUP(A32,[1]速卖通售后单!$A:$C,2,FALSE) -> #N/A
A33: 3066983360464850 | B33: 交易完成 | C33: default firstName default lastName | D33: Alexey Karyazin | E33: 01/13/2026 13:39 | F33: 01/13/2026 13:39 | G33: CN￥ 258.31 | H33: AS-RS2-BK * 1 | I33: rauterbergweg 3b、29221、Celle、Niedersachsen、Germany | J33: alexey karyazin | K33: +49 | L33: 17647336233 | M33: alexeyka@kabelmail.de | N33: rauterbergweg 3b | O33: 29221 | Q33: Celle | R33: Niedersachsen | S33: Germany | T33: SELLER_SHIPPING_DE | U33: Seller Shpping DE :00340434798210049659 | V33: 01/16/2026 09:37 | W33: =VLOOKUP(A33,[1]速卖通售后单!$A:$C,2,FALSE) -> #N/A
A34: 8208505421632938 | B34: 等待买家收货 | C34: default firstName default lastName | D34: Michael Pierno | E34: 01/13/2026 13:33 | F34: 01/13/2026 13:33 | G34: CN￥ 241.76 | H34: JKM@-180in1-BK * 1 | I34: 457 Park Rd、Dingmans ferry、Pennsylvania、United States | J34: Michael Pierno | K34: +1 | L34: 8453210237 | M34: arsenic@aol.com | N34: 457 Park Rd | O34: 18328 | Q34: Dingmans ferry | R34: Pennsylvania | S34: United States | T34: Seller Shpping | U34: Seller Shipping US:9234690382438000150050 | W34: =VLOOKUP(A34,[1]速卖通售后单!$A:$C,2,FALSE) -> #N/A
A35: 3067121851402114 | B35: 等待买家收货 | C35: default firstName default lastName | D35: Michael Da Silva Abreu | E35: 01/13/2026 12:52 | F35: 01/13/2026 12:52 | G35: CN￥ 240.18 | H35: LX-RS66IN1 * 1 | I35: Waldstraße 8、65462、Ginsheim-Gustavsburg、Gross-Gerau、Hessen、Germany | J35: Michael Da Silva Abreu | K35: +49 | L35: 16097691928 | M35: michael.da.silva.abreu@gmail.com | N35: Waldstraße 8 | O35: 65462 | P35: Ginsheim-Gustavsburg | Q35: Gross-Gerau | R35: Hessen | S35: Germany | T35: SELLER_SHIPPING_DE | U35: Seller Shpping DE :00340434798210049642 | W35: =VLOOKUP(A35,[1]速卖通售后单!$A:$C,2,FALSE) -> #N/A
A36: 3067303005021259 | B36: 等待买家收货 | C36: default firstName default lastName | D36: Edu Corominas | E36: 01/13/2026 12:37 | F36: 01/13/2026 12:37 | G36: CN￥ 309.89 | H36: JKM@-180in1-Wh * 1 | I36: 12 Carrer Tenor Viñas 2 piso 2 puerta、Teia、Barcelona、Spain | J36: Eduard Corominas | K36: +34 | L36: 649856314 | M36: eduardcoro@hotmail.com | N36: 12 Carrer Tenor Viñas 2 piso 2 puerta | O36: 08329 | Q36: Teia | R36: Barcelona | S36: Spain | T36: SELLER_SHIPPING_DE | U36: Seller Shpping DE :887890821471 | W36: =VLOOKUP(A36,[1]速卖通售后单!$A:$C,2,FALSE) -> #N/A
A37: 8208003639459399 | B37: 等待买家收货 | C37: default firstName default lastName | D37: Tiffany user | E37: 01/13/2026 09:52 | F37: 01/13/2026 09:52 | G37: CN￥ 274.73 | H37: JKM@-ele180in1-BK * 1 | I37: 1637 county road 307、Poplar bluff、Missouri、United States | J37: Tiffany Chestnut | K37: +1 | L37: 5737723056 | M37: facebook_1009197560917282@aliexpress.com | N37: 1637 county road 307 | O37: 63901 | Q37: Poplar bluff | R37: Missouri | S37: United States | T37: AE_US_SAVER | U37: AE_US_SAVER:CNGF001FL9399000005535228 | W37: =VLOOKUP(A37,[1]速卖通售后单!$A:$C,2,FALSE) -> #N/A
A38: 8208855039512330 | B38: 等待买家收货 | C38: default firstName default lastName | D38: Harrsion Feng | E38: 01/13/2026 08:47 | F38: 01/13/2026 08:47 | G38: CN￥ 274.73 | H38: JKM@-ele180in1-BK * 1 | I38: 8626 108TH ST、Jamaica、New York、United States | J38: Jingquan Feng | K38: 1 | L38: 9172546731 | M38: google_103501381809389016114@aliexpress.com | N38: 8626 108TH ST | O38: 11418 | Q38: Jamaica | R38: New York | S38: United States | T38: AE_US_SAVER | U38: AE_US_SAVER:UUS61E5650866917812 | W38: =VLOOKUP(A38,[1]速卖通售后单!$A:$C,2,FALSE) -> #N/A
A39: 8208393325141995 | B39: 等待买家收货 | C39: default firstName default lastName | D39: jazlynbr1 user | E39: 01/12/2026 22:07 | F39: 01/12/2026 22:07 | G39: CN￥ 267.30 | H39: JKM@-ele180in1-BK * 1 | I39: 960 grand concourse APT 3H、Bronx、New York、United States | J39: Adrian Pero | K39: +1 | L39: 9296310407 | M39: jazlynbr1@hotmail.com | N39: 960 grand concourse APT 3H | O39: 10451 | Q39: Bronx | R39: New York | S39: United States | T39: AE_US_SAVER | U39: AE_US_SAVER:CNGF001FL1995000005593825 | W39: =VLOOKUP(A39,[1]速卖通售后单!$A:$C,2,FALSE) -> #N/A
A40: 8208842077785806 | B40: 等待买家收货 | C40: default firstName default lastName | D40: The Wildcard | E40: 01/12/2026 18:48 | F40: 01/12/2026 18:48 | G40: CN￥ 152.02 | H40: MT-S1-Sliver * 1 | I40: 5540 NW 31st AVE APT 309、Fort lauderdale、Florida、United States | J40: Albert Waldo | K40: +1 | L40: 9547404891 | M40: aawaldo1989@gmail.com | N40: 5540 NW 31st AVE APT 309 | O40: 33309 | Q40: Fort lauderdale | R40: Florida | S40: United States | T40: AE_US_SAVER | U40: AE_US_SAVER:UUS61D5650863379778 | W40: =VLOOKUP(A40,[1]速卖通售后单!$A:$C,2,FALSE) -> #N/A
A41: 8207832744727567 | B41: 等待买家收货 | C41: default firstName default lastName | D41: joey.briguglio user | E41: 01/12/2026 16:57 | F41: 01/12/2026 16:57 | G41: CN￥ 235.22 | H41: JKM@-180in1-BK * 1 | I41: 1614 Scott Street、Clearwater、Florida、United States | J41: Joseph Briguglio | K41: +1 | L41: 8135129758 | M41: joey.briguglio@gmail.com | N41: 1614 Scott Street | O41: 33755 | Q41: Clearwater | R41: Florida | S41: United States | T41: AE_US_SAVER | U41: AE_US_SAVER:UUS61D5650863379690 | W41: =VLOOKUP(A41,[1]速卖通售后单!$A:$C,2,FALSE) -> #N/A
A42: 8208384126047745 | B42: 等待买家收货 | C42: default firstName default lastName | D42: US shopper | E42: 01/12/2026 16:42 | F42: 01/12/2026 16:42 | G42: CN￥ 220.32 | H42: LX-RS66IN1 * 1 | I42: 24671 Coleford Street、Lake forest、California、United States | J42: Lisa Ishimaru | K42: 1 | L42: 2138806621 | M42: ayakun5@hotmail.com | N42: 24671 Coleford Street | O42: 92630 | Q42: Lake forest | R42: California | S42: United States | T42: AE_US_SAVER | U42: AE_US_SAVER:UUS61E5650866984914 | W42: =VLOOKUP(A42,[1]速卖通售后单!$A:$C,2,FALSE) -> #N/A
A43: 8208384122037745 | B43: 订单关闭 | C43: default firstName default lastName | D43: U**r | E43: 01/12/2026 16:37 | F43: 01/12/2026 16:37 | G43: CN￥ 258.88 | H43: GJ-JLLSD-055+RS2 * 1 | I43: *************d Street、Lake forest、California、United States | J43: Lisa********* | K43: 1 | L43: 21****6621 | M43: ayak***@hotmail.com | N43: ************** Street | O43: 92630 | Q43: Lake forest | R43: California | S43: United States | T43: Seller Shpping | W43: =VLOOKUP(A43,[1]速卖通售后单!$A:$C,2,FALSE) -> #N/A
A44: 8208478381543985 | B44: 交易完成 | C44: default firstName default lastName | D44: Chunlan Fang | E44: 01/12/2026 14:15 | F44: 01/12/2026 14:16 | G44: CN￥ 152.02 | H44: MT-S1-Sliver * 1 | I44: 820 50th Street 2 Floor、Brooklyn、New York、United States | J44: Chunlan Fang | K44: +1 | L44: 9172830212 | M44: chunlanfang@hotmail.com | N44: 820 50th Street 2 Floor | O44: 11220 | Q44: Brooklyn | R44: New York | S44: United States | T44: USPS | U44: 美国邮政:9200190382438000050426 | V44: 01/15/2026 14:28 | W44: =VLOOKUP(A44,[1]速卖通售后单!$A:$C,2,FALSE) -> #N/A
A45: 8208468789704669 | B45: 等待买家收货 | C45: default firstName default lastName | D45: Mirwin Robertis | E45: 01/12/2026 06:17 | F45: 01/12/2026 06:17 | G45: CN￥ 231.34 | H45: JKM@-180in1-Wh * 1 | I45: 8440 NW 66th ST JRG246659、Miami、Florida、United States | J45: MIRWIN DANIEL ROBERTIS ROSALES | K45: +1 | L45: 3059991745 | M45: mirwinrobertis@gmail.com | N45: 8440 NW 66th ST JRG246659 | O45: 33166 | Q45: Miami | R45: Florida | S45: United States | T45: AE_US_SAVER | U45: AE_US_SAVER:UUS61D5650863379838 | W45: =VLOOKUP(A45,[1]速卖通售后单!$A:$C,2,FALSE) -> #N/A
A46: 8208466549958574 | B46: 等待买家收货 | C46: default firstName default lastName | D46: cg.kenny1986 user | E46: 01/12/2026 04:53 | F46: 01/12/2026 04:56 | G46: CN￥ 231.34 | H46: JKM@-180in1-Wh * 1 | I46: 36926 266th st、Platte、South Dakota、United States | J46: Kenneth Waldner | K46: +1 | L46: 6053372404 | M46: cg.kenny1986@gmail.com | N46: 36926 266th st | O46: 57369 | Q46: Platte | R46: South Dakota | S46: United States | T46: AE_US_SAVER | U46: AE_US_SAVER:CNGF001FL8574000005471636 | W46: =VLOOKUP(A46,[1]速卖通售后单!$A:$C,2,FALSE) -> #N/A
A47: 8207813785590627 | B47: 订单关闭 | C47: default firstName default lastName | D47: D**h | E47: 01/12/2026 03:49 | F47: 01/12/2026 03:53 | G47: CN￥ 154.88 | H47: MT-S1-Sliver * 1 | I47: **********oulevard、Troy、New York、United States | J47: Doug********* | K47: 1 | L47: 518-****9534 | M47: douglas.p.*****@gmail.com | N47: **********oulevard | O47: 12180 | Q47: Troy | R47: New York | S47: United States | T47: USPS | W47: =VLOOKUP(A47,[1]速卖通售后单!$A:$C,2,FALSE) -> #N/A
A48: 8207717455654231 | B48: 等待买家收货 | C48: default firstName default lastName | D48: joseluis Rayos | E48: 01/12/2026 02:28 | F48: 01/12/2026 02:33 | G48: CN￥ 267.30 | H48: JKM@-ele180in1-BK * 1 | I48: 1970NW 82nd AVE MAD643 MAD 643、Miami、Florida、United States | J48: RustyOdin MAD643 | K48: +1 | L48: 3055978913 | M48: joseluisrayosc2301@gmail.com | N48: 1970NW 82nd AVE MAD643 MAD 643 | O48: 331261049 | Q48: Miami | R48: Florida | S48: United States | T48: AE_US_SAVER | U48: AE_US_SAVER:UUS61D5650863379883 | W48: =VLOOKUP(A48,[1]速卖通售后单!$A:$C,2,FALSE) -> #N/A
A49: 8207752648270738 | B49: 订单关闭 | C49: default firstName default lastName | D49: r**r | E49: 01/11/2026 23:41 | G49: CN￥ 267.30 | H49: JKM@-ele180in1-BK * 1 | I49: ***********oncourse APT 3H、Bronx、New York、United States | J49: Adr******** | K49: +1 | L49: 92****0407 | M49: reckartche*****@hotmail.com | N49: ******************e APT 3H | O49: 10451 | Q49: Bronx | R49: New York | S49: United States | T49: AE_US_SAVER | W49: =VLOOKUP(A49,[1]速卖通售后单!$A:$C,2,FALSE) -> #N/A
A50: 8208816153860738 | B50: 订单关闭 | C50: default firstName default lastName | D50: r**r | E50: 01/11/2026 23:38 | G50: CN￥ 267.30 | H50: JKM@-ele180in1-BK * 1 | I50: ***********oncourse APT 3H、Bronx、New York、United States | J50: Adr******** | K50: +1 | L50: 92****0407 | M50: reckartche*****@hotmail.com | N50: ******************e APT 3H | O50: 10451 | Q50: Bronx | R50: New York | S50: United States | T50: AE_US_SAVER | W50: =VLOOKUP(A50,[1]速卖通售后单!$A:$C,2,FALSE) -> #N/A
A51: 8208460785972844 | B51: 等待买家收货 | C51: default firstName default lastName | D51: Ware Benjamin | E51: 01/11/2026 21:35 | F51: 01/11/2026 21:35 | G51: CN￥ 235.87 | H51: JKM@-180in1-Wh * 1 | I51: 11644 meadowrun CIR、Fort myers、Florida、United States | J51: Benjamin Ware | K51: +1 | L51: 2404726690 | M51: 5dxvhswfrr@privaterelay.appleid.com | N51: 11644 meadowrun CIR | O51: 33913 | Q51: Fort myers | R51: Florida | S51: United States | T51: AE_US_SAVER | U51: AE_US_SAVER:UUS61D5650863379816 | W51: =VLOOKUP(A51,[1]速卖通售后单!$A:$C,2,FALSE) -> 1
A52: 8207960590164319 | B52: 等待买家收货 | C52: default firstName default lastName | D52: Look My | E52: 01/11/2026 21:29 | F52: 01/11/2026 21:29 | G52: CN￥ 213.84 | H52: LX8-TE-250701 * 1 | I52: 2709 E lynx PL、Chandler、Arizona、United States | J52: Michael perzan | K52: +1 | L52: 4807320488 | M52: lookandy@protonmail.com | N52: 2709 E lynx PL | O52: 85249 | Q52: Chandler | R52: Arizona | S52: United States | T52: USPS | U52: 美国邮政:9234690382438000150036 | W52: =VLOOKUP(A52,[1]速卖通售后单!$A:$C,2,FALSE) -> #N/A
A53: 8208597090784166 | B53: 订单关闭 | C53: default firstName default lastName | D53: M**o | E53: 01/11/2026 18:46 | G53: CN￥ 187.27 | H53: XGGJ23110201 * 1 | I53: **************H STREET suite 100 Doral BM-232037、Miami、Florida、United States | J53: Wei******** | K53: +1 | L53: 30****5383 | M53: facebook_4924278********@aliexpress.com | N53: ****************************************M-232037 | O53: 33198 | Q53: Miami | R53: Florida | S53: United States | T53: AE_US_SAVER | W53: =VLOOKUP(A53,[1]速卖通售后单!$A:$C,2,FALSE) -> #N/A
A54: 8207950436316579 | B54: 等待买家收货 | C54: default firstName default lastName | D54: US shopper | E54: 01/11/2026 13:58 | F54: 01/11/2026 13:58 | G54: CN￥ 220.32 | H54: LX-RS66IN1 * 1 | I54: 116 Topaz trl、Syracuse、New York、United States | J54: Roman | K54: +1 | L54: 3154985684 | M54: archie2nd@hotmail.com | N54: 116 Topaz trl | O54: 13219 | Q54: Syracuse | R54: New York | S54: United States | T54: AE_US_SAVER | U54: AE_US_SAVER:UUS61C5650851291662 | W54: =VLOOKUP(A54,[1]速卖通售后单!$A:$C,2,FALSE) -> #N/A
A55: 3067187245191127 | B55: 等待买家收货 | C55: default firstName default lastName | D55: Simo Djuric | E55: 01/11/2026 10:59 | F55: 01/11/2026 10:59 | G55: CN￥ 247.64 | H55: XLW-ele138-BK * 1 | I55: Robert-Koch-Str. 3a 3A、85080、Gaimersheim、Eichstaett、Bayern、Germany | J55: Simo Djuric | K55: +49 | L55: 15153693693 | M55: djuric.s@web.de | N55: Robert-Koch-Str. 3a 3A | O55: 85080 | P55: Gaimersheim | Q55: Eichstaett | R55: Bayern | S55: Germany | T55: SELLER_SHIPPING_DE | U55: Seller Shpping DE :00340434798210048683 | W55: =VLOOKUP(A55,[1]速卖通售后单!$A:$C,2,FALSE) -> #N/A
A56: 8207696098281613 | B56: 等待买家收货 | C56: default firstName default lastName | D56: Grinshpan Napoleon | E56: 01/11/2026 09:10 | F56: 01/11/2026 09:10 | G56: CN￥ 235.87 | H56: JKM@-180in1-Wh * 1 | I56: 22 Division Street、Closter、New Jersey、United States | J56: Napoleon Camero Grinshpan | K56: +1 | L56: 3479159867 | M56: m5jq6rdxx8@privaterelay.appleid.com | N56: 22 Division Street | O56: 07624 | Q56: Closter | R56: New Jersey | S56: United States | T56: AE_US_SAVER | U56: AE_US_SAVER:UUS61C5650851290022 | W56: =VLOOKUP(A56,[1]速卖通售后单!$A:$C,2,FALSE) -> #N/A
A57: 8207696098321613 | B57: 等待买家收货 | C57: default firstName default lastName | D57: Grinshpan Napoleon | E57: 01/11/2026 09:10 | F57: 01/11/2026 09:10 | G57: CN￥ 235.86 | H57: XGGJ23110201-180in1 * 1 | I57: 22 Division Street、Closter、New Jersey、United States | J57: Napoleon Camero Grinshpan | K57: +1 | L57: 3479159867 | M57: m5jq6rdxx8@privaterelay.appleid.com | N57: 22 Division Street | O57: 07624 | Q57: Closter | R57: New Jersey | S57: United States | T57: AE_US_SAVER | U57: AE_US_SAVER:UUS61C5650851289997 | W57: =VLOOKUP(A57,[1]速卖通售后单!$A:$C,2,FALSE) -> #N/A
A58: 8207696098261613 | B58: 等待买家收货 | C58: default firstName default lastName | D58: Grinshpan Napoleon | E58: 01/11/2026 09:10 | F58: 01/11/2026 09:10 | G58: CN￥ 231.34 | H58: JKM@-180in1-Wh * 1 | I58: 22 Division Street、Closter、New Jersey、United States | J58: Napoleon Camero Grinshpan | K58: +1 | L58: 3479159867 | M58: m5jq6rdxx8@privaterelay.appleid.com | N58: 22 Division Street | O58: 07624 | Q58: Closter | R58: New Jersey | S58: United States | T58: AE_US_SAVER | U58: AE_US_SAVER:UUS61C5650851290036 | W58: =VLOOKUP(A58,[1]速卖通售后单!$A:$C,2,FALSE) -> #N/A
A59: 8208576454422220 | B59: 等待买家收货 | C59: default firstName default lastName | D59: David Brown | E59: 01/10/2026 20:20 | F59: 01/10/2026 20:20 | G59: CN￥ 267.30 | H59: JKM@-ele180in1-BK * 1 | I59: 3610 N 2800E、Twin falls、Idaho、United States | J59: David Brown | K59: 1 | L59: 7348079961 | M59: davidkbrown2109@gmail.com | N59: 3610 N 2800E | O59: 83301 | Q59: Twin falls | R59: Idaho | S59: United States | T59: Seller Shpping | U59: Seller Shipping US:GFUS01029305585472 | W59: =VLOOKUP(A59,[1]速卖通售后单!$A:$C,2,FALSE) -> #N/A
A60: 8207679932571762 | B60: 等待买家收货 | C60: default firstName default lastName | D60: Justin Becker | E60: 01/10/2026 13:17 | F60: 01/10/2026 13:17 | G60: CN￥ 267.30 | H60: JKM@-ele180in1-BK * 1 | I60: 1308 bunny lane、Brodheadsville、Pennsylvania、United States | J60: Justin Becker | K60: 610 | L60: 6107394265 | M60: justinbecker4134@gmail.com | N60: 1308 bunny lane | O60: 18322 | Q60: Brodheadsville | R60: Pennsylvania | S60: United States | T60: AE_US_SAVER | U60: AE_US_SAVER:CNGF001FL1762000005202785 | W60: =VLOOKUP(A60,[1]速卖通售后单!$A:$C,2,FALSE) -> #N/A
A61: 8208329240591171 | B61: 等待买家收货 | C61: default firstName default lastName | D61: mark.d.agard user | E61: 01/10/2026 13:10 | F61: 01/10/2026 13:10 | G61: CN￥ 235.22 | H61: JKM@-180in1-BK * 1 | I61: 3912 7th St NE Apt 4、Washington、District of Columbia、United States | J61: Mark Agard | K61: +1 | L61: 5037479749 | M61: mark.d.agard@gmail.com | N61: 3912 7th St NE Apt 4 | O61: 20017 | Q61: Washington | R61: District of Columbia | S61: United States | T61: AE_US_SAVER | U61: AE_US_SAVER:UUS61B5650847485209 | W61: =VLOOKUP(A61,[1]速卖通售后单!$A:$C,2,FALSE) -> #N/A
A62: 8208552378782165 | B62: 等待买家收货 | C62: default firstName default lastName | D62: Kye Morelli | E62: 01/09/2026 19:58 | F62: 01/09/2026 19:58 | G62: CN￥ 267.30 | H62: JKM@-ele180in1-BK * 1 | I62: 105 N 27th ST、Mount vernon、Illinois、United States | J62: kye morelli | K62: +1 | L62: 6183157301 | M62: funguykye@gmail.com | N62: 105 N 27th ST | O62: 62864 | Q62: Mount vernon | R62: Illinois | S62: United States | T62: Seller Shpping | U62: Seller Shipping US:9234690382438000051654 | W62: =VLOOKUP(A62,[1]速卖通售后单!$A:$C,2,FALSE) -> #N/A
A63: 8208551257456386 | B63: 等待买家收货 | C63: default firstName default lastName | D63: Neil Afflalo | E63: 01/09/2026 18:47 | F63: 01/09/2026 18:47 | G63: CN￥ 235.22 | H63: JKM@-180in1-BK * 1 | I63: 9309 willow creek DR P、Montgomery village、Maryland、United States | J63: Neil Afflalo | K63: +1 | L63: 2408486482 | M63: midknightraver25@gmail.com | N63: 9309 willow creek DR P | O63: 20886 | Q63: Montgomery village | R63: Maryland | S63: United States | T63: AE_US_SAVER | U63: AE_US_SAVER:UUS61B5650847485189 | W63: =VLOOKUP(A63,[1]速卖通售后单!$A:$C,2,FALSE) -> #N/A
A64: 3067105007874110 | B64: 等待买家收货 | C64: default firstName default lastName | D64: Fco Javier Glez Faza | E64: 01/09/2026 14:10 | F64: 01/09/2026 14:10 | G64: CN￥ 269.77 | H64: LX-RS66IN1 * 1 | I64: Calle Fuertes Acevedo N62 3E, 33006 Oviedo (Asturias)、Oviedo、Asturias、Spain | J64: Francisco Javier González Faza | K64: +34 | L64: 619069633 | M64: fazastur@hotmail.com | N64: Calle Fuertes Acevedo N62 3E, 33006 Oviedo (Asturias) | O64: 33006 | Q64: Oviedo | R64: Asturias | S64: Spain | T64: SELLER_SHIPPING_DE | U64: Seller Shpping DE :CJ373552609DE | W64: =VLOOKUP(A64,[1]速卖通售后单!$A:$C,2,FALSE) -> #N/A
A65: 8207653535543996 | B65: 等待买家收货 | C65: default firstName default lastName | D65: Pedro Leon | E65: 01/09/2026 09:27 | F65: 01/09/2026 09:29 | G65: CN￥ 231.34 | H65: XGGJ23110201-180in1 * 1 | I65: 2240 NW 114th AVE、Miami、Florida、United States | J65: Felix Ramirez | K65: +1 | L65: 2562561105 | M65: pleon9564@gmail.com | N65: 2240 NW 114th AVE | O65: 33192 | Q65: Miami | R65: Florida | S65: United States | T65: AE_US_SAVER | U65: AE_US_SAVER:UUS61B5650847485175 | W65: =VLOOKUP(A65,[1]速卖通售后单!$A:$C,2,FALSE) -> #N/A
A66: 8207652491310585 | B66: 交易完成 | C66: default firstName default lastName | D66: Jose Ortiz | E66: 01/09/2026 08:31 | F66: 01/09/2026 08:31 | G66: CN￥ 213.84 | H66: LX8-TE-250701 * 1 | I66: 9950 club creek DR 1312、Houston、Texas、United States | J66: Jose Ortiz | K66: +1 | L66: 8328457466 | M66: rubenjoseortizruiz@gmail.com | N66: 9950 club creek DR 1312 | O66: 77036 | Q66: Houston | R66: Texas | S66: United States | T66: AE_US_SAVER | U66: AE_US_SAVER:UUS61B5650847427605 | V66: 01/16/2026 11:37 | W66: =VLOOKUP(A66,[1]速卖通售后单!$A:$C,2,FALSE) -> #N/A
A67: 8208533250981564 | B67: 等待买家收货 | C67: default firstName default lastName | D67: Aaron Wallace | E67: 01/09/2026 03:40 | F67: 01/09/2026 03:41 | G67: CN￥ 220.32 | H67: LX-RS66IN1 * 1 | I67: 925 W. Gregory Rd.、Phoenix、Arizona、United States | J67: Dallas Ryan | K67: +1 | L67: 6023178788 | M67: aaron@inspireuplift.com | N67: 925 W. Gregory Rd. | O67: 85041 | Q67: Phoenix | R67: Arizona | S67: United States | T67: AE_US_SAVER | U67: AE_US_SAVER:UUS61B5650847427632 | W67: =VLOOKUP(A67,[1]速卖通售后单!$A:$C,2,FALSE) -> #N/A
A68: 8208531655090048 | B68: 等待买家收货 | C68: default firstName default lastName | D68: Natalia Gonzalez | E68: 01/09/2026 02:00 | F68: 01/09/2026 02:00 | G68: CN￥ 144.34 | H68: GJ-JLLSD-055+RS1 * 1 | I68: 1655 Eberts Dr、San martin、California、United States | J68: Kyle Rosenzweig | K68: +1 | L68: 4084380383 | M68: nataliag@internetincomellc.com | N68: 1655 Eberts Dr | O68: 95046 | Q68: San martin | R68: California | S68: United States | T68: Seller Shpping | U68: Seller Shipping US:GFUS01029303753984 | W68: =VLOOKUP(A68,[1]速卖通售后单!$A:$C,2,FALSE) -> #N/A
A69: 8207683607860048 | B69: 等待买家收货 | C69: default firstName default lastName | D69: Natalia Gonzalez | E69: 01/09/2026 01:59 | F69: 01/09/2026 01:59 | G69: CN￥ 144.34 | H69: GJ-JLLSD-055+RS1 * 1 | I69: 1655 Eberts Dr、San martin、California、United States | J69: Kyle Rosenzweig | K69: +1 | L69: 4084380383 | M69: nataliag@internetincomellc.com | N69: 1655 Eberts Dr | O69: 95046 | Q69: San martin | R69: California | S69: United States | T69: Seller Shpping | U69: Seller Shipping US:GFUS01029303492992 | W69: =VLOOKUP(A69,[1]速卖通售后单!$A:$C,2,FALSE) -> #N/A
A70: 8207683767090048 | B70: 订单关闭 | C70: default firstName default lastName | D70: N**z | E70: 01/09/2026 01:58 | F70: 01/09/2026 01:58 | G70: CN￥ 144.34 | H70: GJ-JLLSD-055+RS1 * 1 | I70: **********nd Rd B3 City of Orange、Orange、New Jersey、United States | J70: Crys******** | K70: +356 | L70: 71****0299 | M70: nata****@internetincomellc.com | N70: *************************f Orange | O70: 07050 | Q70: Orange | R70: New Jersey | S70: United States | T70: Seller Shpping | W70: =VLOOKUP(A70,[1]速卖通售后单!$A:$C,2,FALSE) -> #N/A
A71: 3067338066936631 | B71: 交易完成 | C71: default firstName default lastName | D71: gianluca parlato | E71: 01/08/2026 22:54 | F71: 01/08/2026 22:54 | G71: CN￥ 264.61 | H71: MT-Ele68in-1 * 1 | I71: via enrico tazzoli 82、19125、La Spezia、La Spezia、Liguria、Italy | J71: parlato gianluca | K71: +39 | L71: 3458113963 | M71: gianlucaparlato@libero.it | N71: via enrico tazzoli 82 | O71: 19125 | P71: La Spezia | Q71: La Spezia | R71: Liguria | S71: Italy | T71: SELLER_SHIPPING_DE | U71: Seller Shpping DE :1Z10GY170420220820 | V71: 01/14/2026 12:03 | W71: =VLOOKUP(A71,[1]速卖通售后单!$A:$C,2,FALSE) -> #N/A
A72: 8207667767753996 | B72: 订单关闭 | C72: default firstName default lastName | D72: P**n | E72: 01/08/2026 10:59 | G72: CN￥ 231.34 | H72: XGGJ23110201-180in1 * 1 | I72: *********14th AVE、Miami、Florida、United States | J72: Feli********* | K72: +1 | L72: 25****1105 | M72: pleon9***@gmail.com | N72: **********4th AVE | O72: 33192 | Q72: Miami | R72: Florida | S72: United States | T72: AE_US_SAVER | W72: =VLOOKUP(A72,[1]速卖通售后单!$A:$C,2,FALSE) -> #N/A
A73: 8207876431616956 | B73: 等待买家收货 | C73: default firstName default lastName | D73: Abel Arroyo | E73: 01/08/2026 10:33 | F73: 01/08/2026 10:33 | G73: CN￥ 267.30 | H73: JKM@-ele180in1-BK * 1 | I73: 4238 North 16th Drive、Phoenix、Arizona、United States | J73: Cesar A Arroyo Traverso | K73: +1 | L73: 6266659133 | M73: abel.arroyot@gmail.com | N73: 4238 North 16th Drive | O73: 85015 | Q73: Phoenix | R73: Arizona | S73: United States | T73: AE_US_SAVER | U73: AE_US_SAVER:UUS61B5650847427624 | W73: =VLOOKUP(A73,[1]速卖通售后单!$A:$C,2,FALSE) -> #N/A
A74: 8208373182663996 | B74: 订单关闭 | C74: default firstName default lastName | D74: P**n | E74: 01/08/2026 07:12 | G74: CN￥ 235.86 | H74: XGGJ23110201-180in1 * 1 | I74: *********14th AVE、Miami、Florida、United States | J74: Feli********* | K74: +1 | L74: 25****1105 | M74: pleon9***@gmail.com | N74: **********4th AVE | O74: 33192 | Q74: Miami | R74: Florida | S74: United States | T74: AE_US_SAVER | W74: =VLOOKUP(A74,[1]速卖通售后单!$A:$C,2,FALSE) -> #N/A
A75: 8207862116031243 | B75: 等待买家收货 | C75: default firstName default lastName | D75: Omar Salado Villalaz | E75: 01/07/2026 20:36 | F75: 01/07/2026 21:03 | G75: CN￥ 231.34 | H75: JKM@-180in1-Wh * 1 | I75: 1966 NW 82ND AVE CCE3609、Miami、Florida、United States | J75: Omar Alexander Salado CCE | K75: +1 | L75: 3055978913 | M75: omar9salado@gmail.com | N75: 1966 NW 82ND AVE CCE3609 | O75: 33126 | Q75: Miami | R75: Florida | S75: United States | T75: AE_US_SAVER | U75: AE_US_SAVER:UUS6185650828975913 | W75: =VLOOKUP(A75,[1]速卖通售后单!$A:$C,2,FALSE) -> #N/A
A76: 8207709304447780 | B76: 等待买家收货 | C76: default firstName default lastName | D76: kaming lam | E76: 01/07/2026 17:10 | F76: 01/07/2026 17:10 | G76: CN￥ 144.34 | H76: GJ-JLLSD-055+RS1 * 1 | I76: 1160 Ala Napunani Street #1805、Honolulu、Hawaii、United States | J76: Ka ming lam | K76: 1 | L76: 8087410896 | M76: ming5ming76@gmail.com | N76: 1160 Ala Napunani Street #1805 | O76: 96818 | Q76: Honolulu | R76: Hawaii | S76: United States | T76: Seller Shpping | U76: Seller Shipping US:GFUS01028738052289 | W76: =VLOOKUP(A76,[1]速卖通售后单!$A:$C,2,FALSE) -> #N/A
A77: 3066831458848361 | B77: 交易完成 | C77: default firstName default lastName | D77: andrea.vergerio a | E77: 01/07/2026 14:40 | F77: 01/07/2026 14:40 | G77: CN￥ 306.84 | H77: JKM@-180in1-BK * 1 | I77: Via Giovanni Pascoli, Jerago 11、21040、Jerago con Orago、Varese、Lombardia、Italy | J77: Andrea Vergerio | K77: +39 | L77: 3209252329 | M77: andrea.vergerio@alice.it | N77: Via Giovanni Pascoli, Jerago 11 | O77: 21040 | P77: Jerago con Orago | Q77: Varese | R77: Lombardia | S77: Italy | T77: SELLER_SHIPPING_DE | U77: Seller Shpping DE :887728238406 | V77: 01/13/2026 11:17 | W77: =VLOOKUP(A77,[1]速卖通售后单!$A:$C,2,FALSE) -> #N/A
A78: 3067362793500991 | B78: 交易完成 | C78: default firstName default lastName | D78: Francisco Javier Licera | E78: 01/07/2026 08:45 | F78: 01/07/2026 08:45 | G78: CN￥ 311.35 | H78: JKM@-180in1-BK * 1 | I78: Villa de Marin, 45 1-B、Madrid、Madrid、Spain | J78: francisco javier Licera | K78: +34 | L78: 639174528 | M78: pacolicera@gmail.com | N78: Villa de Marin, 45 1-B | O78: 28029 | Q78: Madrid | R78: Madrid | S78: Spain | T78: SELLER_SHIPPING_DE | U78: Seller Shpping DE :887728237991 | V78: 01/14/2026 13:43 | W78: =VLOOKUP(A78,[1]速卖通售后单!$A:$C,2,FALSE) -> #N/A
A79: 8207631440839342 | B79: 等待买家收货 | C79: default firstName default lastName | D79: Ezequiel salcie | E79: 01/07/2026 08:22 | F79: 01/07/2026 08:22 | G79: CN￥ 220.32 | H79: LX-RS66IN1 * 1 | I79: 4624 NW 74th Ave Unit 4、Miami、Florida、United States | J79: Ezequiel Salcie D01-383024 Salcie | K79: +1 | L79: 3055993939 | M79: salcie18@gmail.com | N79: 4624 NW 74th Ave Unit 4 | O79: 33166 | Q79: Miami | R79: Florida | S79: United States | T79: AE_US_SAVER | U79: AE_US_SAVER:UUS6185650827679638 | W79: =VLOOKUP(A79,[1]速卖通售后单!$A:$C,2,FALSE) -> #N/A
A80: 8208481579244356 | B80: 订单关闭 | C80: default firstName default lastName | D80: A**m | E80: 01/07/2026 08:09 | F80: 01/07/2026 08:09 | G80: CN￥ 235.22 | H80: JKM@-180in1-BK * 1 | I80: ********n Avenue、Harrisburg、Pennsylvania、United States | J80: Avi******* | K80: 1 | L80: 70****8279 | M80: nguyen*****@gmail.com | N80: ********* Avenue | O80: 17109 | Q80: Harrisburg | R80: Pennsylvania | S80: United States | T80: AE_US_SAVER | W80: =VLOOKUP(A80,[1]速卖通售后单!$A:$C,2,FALSE) -> #N/A
A81: 3067000998531438 | B81: 等待买家收货 | C81: default firstName default lastName | D81: Rafa Medina | E81: 01/07/2026 06:50 | F81: 01/07/2026 06:50 | G81: CN￥ 311.35 | H81: JKM@-180in1-BK * 1 | I81: C/Alfonso XI N°31 Bajo Almacold、Alcala la Real、Jaen、Spain | J81: Rafael medina | K81: +34 | L81: 608734931 | M81: r_medina_n@hotmail.com | N81: C/Alfonso XI N°31 Bajo Almacold | O81: 23680 | Q81: Alcala la Real | R81: Jaen | S81: Spain | T81: SELLER_SHIPPING_DE | U81: Seller Shpping DE :887728237064 | W81: =VLOOKUP(A81,[1]速卖通售后单!$A:$C,2,FALSE) -> #N/A
A82: 8207686023642262 | B82: 等待买家收货 | C82: default firstName default lastName | D82: Spurgeon Brian | E82: 01/06/2026 20:03 | F82: 01/06/2026 20:03 | G82: CN￥ 220.32 | H82: LX-RS66IN1 * 1 | I82: 7497 avon belden RD、North ridgeville、Ohio、United States | J82: Brian Spurgeon | K82: +1 | L82: 4406668523 | M82: cc8d8fz825@privaterelay.appleid.com | N82: 7497 avon belden RD | O82: 44039 | Q82: North ridgeville | R82: Ohio | S82: United States | T82: AE_US_SAVER | U82: AE_US_SAVER:UUS6185650827679622 | W82: =VLOOKUP(A82,[1]速卖通售后单!$A:$C,2,FALSE) -> #N/A
A83: 8207578013461540 | B83: 交易完成 | C83: default firstName default lastName | D83: Lord Remorin | E83: 01/06/2026 14:12 | F83: 01/06/2026 14:13 | G83: CN￥ 235.22 | H83: JKM@-180in1-BK * 1 | I83: 6927 131st St SE、Snohomish、Washington、United States | J83: Lord Remorin | K83: +1 | L83: 2142400853 | M83: lord_remorin@yahoo.com | N83: 6927 131st St SE | O83: 98296 | Q83: Snohomish | R83: Washington | S83: United States | T83: Seller Shpping | U83: Seller Shipping US:9234690382438000051623 | V83: 01/14/2026 16:59 | W83: =VLOOKUP(A83,[1]速卖通售后单!$A:$C,2,FALSE) -> #N/A
A84: 8208320064187831 | B84: 等待买家收货 | C84: default firstName default lastName | D84: Brandon Tucker | E84: 01/06/2026 09:47 | F84: 01/06/2026 09:47 | G84: CN￥ 235.87 | H84: JKM@-180in1-Wh * 1 | I84: 25184 state route mm、Farmington、Missouri、United States | J84: Brandon Tucker | K84: +1 | L84: 5733667796 | M84: brandon450t@gmail.com | N84: 25184 state route mm | O84: 63640 | Q84: Farmington | R84: Missouri | S84: United States | T84: AE_US_SAVER | U84: AE_US_SAVER:CNGF001FL7831000005029464 | W84: =VLOOKUP(A84,[1]速卖通售后单!$A:$C,2,FALSE) -> #N/A
A85: 8208667994497557 | B85: 交易完成 | C85: default firstName default lastName | D85: jacob bird | E85: 01/06/2026 08:27 | F85: 01/06/2026 08:27 | G85: CN￥ 231.34 | H85: JKM@-180in1-Wh * 1 | I85: 1975 park DR、Lebanon、Oregon、United States | J85: jacob bird | K85: +1 | L85: 5417402493 | M85: jacobbird45@gmail.com | N85: 1975 park DR | O85: 97355 | Q85: Lebanon | R85: Oregon | S85: United States | T85: Seller Shpping | U85: Seller Shipping US:9234690382438000051630 | V85: 01/12/2026 15:24 | W85: =VLOOKUP(A85,[1]速卖通售后单!$A:$C,2,FALSE) -> #N/A
A86: 3066827862468402 | B86: 等待买家收货 | C86: default firstName default lastName | D86: Fabricio Paladines Grefa | E86: 01/06/2026 08:20 | F86: 01/06/2026 08:21 | G86: CN￥ 311.35 | H86: JKM@-180in1-BK * 1 | I86: Calle Antonio García N,9 - planta 3 . 30700 Torre-Pacheco (Murcia), Spain calle Antonio García N,9 - planta 3、Torre-Pacheco、Murcia、Spain | J86: fabricio paladines | K86: +34 | L86: 722346508 | M86: alba1765az@gmail.com | N86: Calle Antonio García N,9 - planta 3 . 30700 Torre-Pacheco (Murcia), Spain calle Antonio García N,9 - planta 3 | O86: 30700 | Q86: Torre-Pacheco | R86: Murcia | S86: Spain | T86: SELLER_SHIPPING_DE | U86: Seller Shpping DE :887691121738 | W86: =VLOOKUP(A86,[1]速卖通售后单!$A:$C,2,FALSE) -> #N/A
A87: 8208225160146618 | B87: 交易完成 | C87: default firstName default lastName | D87: Kory Thompson | E87: 01/06/2026 08:07 | F87: 01/06/2026 08:07 | G87: CN￥ 267.30 | H87: JKM@-ele180in1-BK * 1 | I87: 185 megan ln、Columbus、Mississippi、United States | J87: Kory Thompson | K87: 520 | L87: 5202614518 | M87: google_114245910960735007454@aliexpress.com | N87: 185 megan ln | O87: 39705 | Q87: Columbus | R87: Mississippi | S87: United States | T87: Seller Shpping | U87: Seller Shipping US:9234690382438000051647 | V87: 01/10/2026 10:27 | W87: =VLOOKUP(A87,[1]速卖通售后单!$A:$C,2,FALSE) -> #N/A
A88: 8207803078945088 | B88: 交易完成 | C88: default firstName default lastName | D88: thisisnotmyrealemailaddress007 user | E88: 01/05/2026 19:01 | F88: 01/05/2026 19:01 | G88: CN￥ 308.45 | H88: JKM@-ele180in1-Wh * 1 | I88: 30755 via la cresta、Rancho palos verdes、California、United States | J88: Kevin Ghaffari | K88: +1 | L88: 3103477447 | M88: thisisnotmyrealemailaddress007@gmail.com | N88: 30755 via la cresta | O88: 90275 | Q88: Rancho palos verdes | R88: California | S88: United States | T88: AE_US_SAVER | U88: AE_US_SAVER:UUS6165650815393317 | V88: 01/13/2026 13:38 | W88: =VLOOKUP(A88,[1]速卖通售后单!$A:$C,2,FALSE) -> #N/A
A89: 8208209569918445 | B89: 交易完成 | C89: default firstName default lastName | D89: ae281405 user | E89: 01/05/2026 17:51 | F89: 01/05/2026 17:51 | G89: CN￥ 267.30 | H89: JKM@-ele180in1-BK * 1 | I89: 1636 NW 82nd Ave (Carlos Daniel Lazo Lobo 32598)、Doral、Florida、United States | J89: Carlos Daniel Lazo Lobo | K89: +1 | L89: 3053285038 | M89: jerry_smt@outlook.com | N89: 1636 NW 82nd Ave (Carlos Daniel Lazo Lobo 32598) | O89: 33126 | Q89: Doral | R89: Florida | S89: United States | T89: AE_US_SAVER | U89: AE_US_SAVER:UUS6165650815485429 | V89: 01/14/2026 07:31 | W89: =VLOOKUP(A89,[1]速卖通售后单!$A:$C,2,FALSE) -> #N/A
A90: 8207585769277790 | B90: 订单关闭 | C90: default firstName default lastName | D90: D**z | E90: 01/05/2026 17:32 | G90: CN￥ 274.73 | H90: JKM@-ele180in1-BK * 1 | I90: *3 Elm St Apt 1、Marblehead、Massachusetts、United States | J90: Dan******* | K90: 1 | L90: 97****9102 | M90: dannyj****@gmail.com | N90: *******St Apt 1 | O90: 01945 | Q90: Marblehead | R90: Massachusetts | S90: United States | T90: AE_US_SAVER | W90: =VLOOKUP(A90,[1]速卖通售后单!$A:$C,2,FALSE) -> #N/A
A91: 3066799062387709 | B91: 交易完成 | C91: default firstName default lastName | D91: Alexei Frank | E91: 01/05/2026 17:05 | F91: 01/05/2026 17:05 | G91: CN￥ 247.64 | H91: XLW-ele138-BK * 1 | I91: Im Marienfried 34、53773、Hennef、Rhein-Sieg-Kreis、Nordrhein-Westfalen、Germany | J91: Alexei Frank | K91: +49 | L91: 15738163543 | M91: alexfrank16@web.de | N91: Im Marienfried 34 | O91: 53773 | P91: Hennef | Q91: Rhein-Sieg-Kreis | R91: Nordrhein-Westfalen | S91: Germany | T91: SELLER_SHIPPING_DE | U91: Seller Shpping DE :00340434798210047273 | V91: 01/13/2026 11:26 | W91: =VLOOKUP(A91,[1]速卖通售后单!$A:$C,2,FALSE) -> #N/A
A92: 3067269679549350 | B92: 订单关闭 | C92: default firstName default lastName | D92: S**s | E92: 01/05/2026 13:47 | F92: 01/05/2026 13:47 | G92: CN￥ 311.35 | H92: JKM@-180in1-BK * 1 | I92: **********************************), Spain 16 3C、Poio、Pontevedra、Spain | J92: Santi*********** | K92: +34 | L92: 6****4120 | M92: google_10473290525**********@aliexpress.com | N92: ****************************************in 16 3C | O92: 36163 | Q92: Poio | R92: Pontevedra | S92: Spain | T92: SELLER_SHIPPING_DE | W92: =VLOOKUP(A92,[1]速卖通售后单!$A:$C,2,FALSE) -> #N/A
A93: 3066902996968666 | B93: 交易完成 | C93: default firstName default lastName | D93: Antonio Di Fabio | E93: 01/05/2026 10:21 | F93: 01/05/2026 10:21 | G93: CN￥ 306.84 | H93: JKM@-180in1-BK * 1 | I93: Civitella del Tronto, via collina n.8 8、64010、Teramo、Abruzzo、Italy | J93: Antonio Di Fabio | K93: +39 | L93: 3898535623 | M93: aantonio.adf@gmail.com | N93: Civitella del Tronto, via collina n.8 8 | O93: 64010 | Q93: Teramo | R93: Abruzzo | S93: Italy | T93: SELLER_SHIPPING_DE | U93: Seller Shpping DE :887657901103 | V93: 01/14/2026 10:22 | W93: =VLOOKUP(A93,[1]速卖通售后单!$A:$C,2,FALSE) -> #N/A
A94: 3067149426549203 | B94: 交易完成 | C94: default firstName default lastName | D94: stefano micheli | E94: 01/05/2026 06:31 | F94: 01/05/2026 06:31 | G94: CN￥ 306.84 | H94: JKM@-180in1-Wh * 1 | I94: via San Giorgio 3037 interno 3、47522、Cesena、Forli-Cesena、Emilia-Romagna、Italy | J94: micheli stefano | K94: +39 | L94: 3922372349 | M94: stefanomicheli63@alice.it | N94: via San Giorgio 3037 interno 3 | O94: 47522 | P94: Cesena | Q94: Forli-Cesena | R94: Emilia-Romagna | S94: Italy | T94: SELLER_SHIPPING_DE | U94: Seller Shpping DE :887657899923 | V94: 01/12/2026 05:28 | W94: =VLOOKUP(A94,[1]速卖通售后单!$A:$C,2,FALSE) -> #N/A
A95: 3067149345485104 | B95: 交易完成 | C95: default firstName default lastName | D95: Jose Ramon La Iglesia Lozano | E95: 01/05/2026 06:25 | F95: 01/05/2026 06:25 | G95: CN￥ 311.35 | H95: JKM@-180in1-BK * 1 | I95: Calle Lorenzo Soto, 30800 Lorca (Murcia), Spain 4 Ático E、Lorca、Murcia、Spain | J95: Jose Ramón La Iglesia Lozano | K95: +34 | L95: 615943083 | M95: jlaiglesialozano2@gmail.com | N95: Calle Lorenzo Soto, 30800 Lorca (Murcia), Spain 4 Ático E | O95: 30800 | Q95: Lorca | R95: Murcia | S95: Spain | T95: SELLER_SHIPPING_DE | U95: Seller Shpping DE :887657901114 | V95: 01/13/2026 07:05 | W95: =VLOOKUP(A95,[1]速卖通售后单!$A:$C,2,FALSE) -> #N/A
A96: 3066763469582869 | B96: 交易完成 | C96: default firstName default lastName | D96: Vampirnazi666 user | E96: 01/05/2026 03:23 | F96: 01/05/2026 03:23 | G96: CN￥ 265.16 | H96: JKM@-180in1-Wh * 1 | I96: Hochstadtweg 16、87600、Kaufbeuren、Kaufbeuren、Bayern、Germany | J96: Julian Radmüller | K96: +49 | L96: 15117278907 | M96: Vampirnazi666@gmail.com | N96: Hochstadtweg 16 | O96: 87600 | P96: Kaufbeuren | Q96: Kaufbeuren | R96: Bayern | S96: Germany | T96: SELLER_SHIPPING_DE | U96: Seller Shpping DE :00340434798210047280 | V96: 01/11/2026 11:49 | W96: =VLOOKUP(A96,[1]速卖通售后单!$A:$C,2,FALSE) -> #N/A
A97: 8207779872080641 | B97: 等待买家收货 | C97: default firstName default lastName | D97: Osama Abumayyaleh | E97: 01/04/2026 23:58 | F97: 01/04/2026 23:58 | G97: CN￥ 241.76 | H97: JKM@-180in1-BK * 1 | I97: 7795 Van Buren St NE, Minneapolis、Spring lake park、Minnesota、United States | J97: Osama Abumayyaleh | K97: +1 | L97: 6124005237 | M97: us20260104m2nw_15064@aliexpress.com | N97: 7795 Van Buren St NE, Minneapolis | O97: 55432 | Q97: Spring lake park | R97: Minnesota | S97: United States | T97: AE_US_SAVER | U97: AE_US_SAVER:UUS6165650815482487 | W97: =VLOOKUP(A97,[1]速卖通售后单!$A:$C,2,FALSE) -> #N/A
A98: 8207564407081564 | B98: 交易完成 | C98: default firstName default lastName | D98: Aaron Wallace | E98: 01/04/2026 22:29 | F98: 01/04/2026 22:36 | G98: CN￥ 220.32 | H98: LX-RS66IN1 * 1 | I98: 938 Lusted Ln、Batavia、Illinois、United States | J98: Marc Parker | K98: +1 | L98: 6303269416 | M98: aaron@inspireuplift.com | N98: 938 Lusted Ln | O98: 60510 | Q98: Batavia | R98: Illinois | S98: United States | T98: AE_US_SAVER | U98: AE_US_SAVER:UUS6165650815482495 | V98: 01/14/2026 12:05 | W98: =VLOOKUP(A98,[1]速卖通售后单!$A:$C,2,FALSE) -> #N/A
A99: 8208625598789552 | B99: 交易完成 | C99: default firstName default lastName | D99: Nadav Goshen | E99: 01/04/2026 19:59 | F99: 01/04/2026 19:59 | G99: CN￥ 154.88 | H99: MT-S1-Sliver * 1 | I99: 155 West 68th Street Apt 1625、New york、New York、United States | J99: Nadav Goshen | K99: +1 | L99: 3477537066 | M99: nadav@goshen.cc | N99: 155 West 68th Street Apt 1625 | O99: 10023 | Q99: New york | R99: New York | S99: United States | T99: USPS | U99: 美国邮政:9200190408166800097750 | V99: 01/13/2026 11:46 | W99: =VLOOKUP(A99,[1]速卖通售后单!$A:$C,2,FALSE) -> #N/A
A100: 8208172201848848 | B100: 交易完成 | C100: default firstName default lastName | D100: Richard Quiroz | E100: 01/04/2026 11:26 | F100: 01/04/2026 11:26 | G100: CN￥ 267.30 | H100: JKM@-ele180in1-BK * 1 | I100: 8626 Eagle Peak、Helotes、Texas、United States | J100: Richard Quiroz | K100: 1 | L100: 2103866393 | M100: rquiroz3@att.net | N100: 8626 Eagle Peak | O100: 78023 | Q100: Helotes | R100: Texas | S100: United States | T100: AE_US_SAVER | U100: AE_US_SAVER:UUS6165650815393331 | V100: 01/10/2026 11:26 | W100: =VLOOKUP(A100,[1]速卖通售后单!$A:$C,2,FALSE) -> #N/A
...
